Metadata-Version: 2.1
Name: dktest
Version: 1.0.3
Summary: Web Scraping Library
Home-page: UNKNOWN
Author: DataKund
Author-email: datakund@gmail.com
License: Apache License 2.0
Platform: UNKNOWN
